webframe/__init__.py
webframe/core.py
webframe/server.py
voidwebframe-0.1.dist-info/METADATA
voidwebframe-0.1.dist-info/WHEEL
voidwebframe-0.1.dist-info/top_level.txt
voidwebframe-0.1.dist-info/RECORD
