Metadata-Version: 2.1
Name: voidwebframe
Version: 0.1
Summary: A simple Web Framework written for simplicity
Author: Syntax
Author-email: krzysztof.gasiewski@tuta.io
Classifier: Programming Language :: Python :: 3
Classifier: License :: OSI Approved :: MIT License
Classifier: Operating System :: OS Independent
